[{"id":849565,"name":"mjy2002","first_name":"ma","last_name":"junyu","url":"https:\/\/api.thingiverse.com\/users\/mjy2002","public_url":"https:\/\/www.thingiverse.com\/mjy2002","thumbnail":"https:\/\/www.thingiverse.com\/img\/default\/avatar\/avatar_default_thumb_medium.jpg"},{"id":539765,"name":"Zizixa","first_name":"michael","last_name":"kruis","url":"https:\/\/api.thingiverse.com\/users\/Zizixa","public_url":"https:\/\/www.thingiverse.com\/Zizixa","thumbnail":"https:\/\/cdn.thingiverse.com\/renders\/26\/e0\/9a\/fb\/9d\/jo_thumb_medium.jpg"},{"id":659348,"name":"diogenesbecker","first_name":"Diogenes","last_name":"Becker","url":"https:\/\/api.thingiverse.com\/users\/diogenesbecker","public_url":"https:\/\/www.thingiverse.com\/diogenesbecker","thumbnail":"https:\/\/cdn.thingiverse.com\/renders\/d5\/77\/66\/7a\/a1\/DiogenesBecker_thumb_medium.jpg"},{"id":118994,"name":"mignolo4","first_name":"mignolo4","last_name":"","url":"https:\/\/api.thingiverse.com\/users\/mignolo4","public_url":"https:\/\/www.thingiverse.com\/mignolo4","thumbnail":"https:\/\/www.thingiverse.com\/img\/default\/avatar\/avatar_default_thumb_medium.jpg"},{"id":548881,"name":"LCHROY","first_name":"Roy","last_name":"Lin","url":"https:\/\/api.thingiverse.com\/users\/LCHROY","public_url":"https:\/\/www.thingiverse.com\/LCHROY","thumbnail":"https:\/\/cdn.thingiverse.com\/renders\/cc\/21\/39\/e2\/01\/1efaaea23c39daaad2bb2bca4a514604_thumb_medium.jpg"},{"id":539949,"name":"freetwhss","first_name":"peter","last_name":"huang","url":"https:\/\/api.thingiverse.com\/users\/freetwhss","public_url":"https:\/\/www.thingiverse.com\/freetwhss","thumbnail":"https:\/\/www.thingiverse.com\/img\/default\/avatar\/avatar_default_thumb_medium.jpg"},{"id":579526,"name":"mrtaz69","first_name":"Tanner","last_name":"Daniel","url":"https:\/\/api.thingiverse.com\/users\/mrtaz69","public_url":"https:\/\/www.thingiverse.com\/mrtaz69","thumbnail":"https:\/\/www.thingiverse.com\/img\/default\/avatar\/avatar_default_thumb_medium.jpg"},{"id":468948,"name":"varsanyim","first_name":"Martina","last_name":"Varsanyi","url":"https:\/\/api.thingiverse.com\/users\/varsanyim","public_url":"https:\/\/www.thingiverse.com\/varsanyim","thumbnail":"https:\/\/cdn.thingiverse.com\/renders\/1e\/43\/5c\/2f\/6c\/profil_thumb_medium.jpg"},{"id":250074,"name":"votoms92","first_name":"SU","last_name":"ROGER","url":"https:\/\/api.thingiverse.com\/users\/votoms92","public_url":"https:\/\/www.thingiverse.com\/votoms92","thumbnail":"https:\/\/www.thingiverse.com\/img\/default\/avatar\/avatar_default_thumb_medium.jpg"},{"id":166581,"name":"djehlke","first_name":"Dan","last_name":"Ehlke","url":"https:\/\/api.thingiverse.com\/users\/djehlke","public_url":"https:\/\/www.thingiverse.com\/djehlke","thumbnail":"https:\/\/www.thingiverse.com\/img\/default\/avatar\/avatar_default_thumb_medium.jpg"},{"id":301174,"name":"ZhilDV","first_name":"Dmitry","last_name":"Zh","url":"https:\/\/api.thingiverse.com\/users\/ZhilDV","public_url":"https:\/\/www.thingiverse.com\/ZhilDV","thumbnail":"https:\/\/cdn.thingiverse.com\/renders\/69\/de\/90\/71\/66\/d2b5ca33bd970f64a6301fa75ae2eb22_thumb_medium.jpg"},{"id":360064,"name":"grayfox100986","first_name":"dan","last_name":"","url":"https:\/\/api.thingiverse.com\/users\/grayfox100986","public_url":"https:\/\/www.thingiverse.com\/grayfox100986","thumbnail":"https:\/\/www.thingiverse.com\/img\/default\/avatar\/avatar_maker_thumb_medium.jpg"},{"id":59212,"name":"3DMD","first_name":"Dr.","last_name":"Craig","url":"https:\/\/api.thingiverse.com\/users\/3DMD","public_url":"https:\/\/www.thingiverse.com\/3DMD","thumbnail":"https:\/\/cdn.thingiverse.com\/renders\/ae\/57\/a7\/d5\/29\/CCK3_thumb_medium.jpg"},{"id":99184,"name":"Dampre","first_name":"Philip","last_name":"Evans","url":"https:\/\/api.thingiverse.com\/users\/Dampre","public_url":"https:\/\/www.thingiverse.com\/Dampre","thumbnail":"https:\/\/cdn.thingiverse.com\/renders\/30\/5b\/fc\/0d\/93\/73112_1637604493457_6255602_n_thumb_medium.jpg"},{"id":29809,"name":"kirkram","first_name":"kirkram","last_name":"","url":"https:\/\/api.thingiverse.com\/users\/kirkram","public_url":"https:\/\/www.thingiverse.com\/kirkram","thumbnail":"https:\/\/www.thingiverse.com\/img\/default\/avatar\/avatar_default_thumb_medium.jpg"},{"id":19807,"name":"htsrjdrouse","first_name":"Richard","last_name":"Rouse","url":"https:\/\/api.thingiverse.com\/users\/htsrjdrouse","public_url":"https:\/\/www.thingiverse.com\/htsrjdrouse","thumbnail":"https:\/\/cdn.thingiverse.com\/renders\/7b\/66\/48\/8c\/6c\/sm_thumb_medium.jpg"},{"id":31023,"name":"zanahade","first_name":"Zander","last_name":"Aengus McHade","url":"https:\/\/api.thingiverse.com\/users\/zanahade","public_url":"https:\/\/www.thingiverse.com\/zanahade","thumbnail":"https:\/\/cdn.thingiverse.com\/renders\/05\/e0\/b5\/aa\/77\/395800_2520076487178_863416904_n_thumb_medium.jpg"},{"id":30370,"name":"saywhat","first_name":"Michael","last_name":"Pedesen","url":"https:\/\/api.thingiverse.com\/users\/saywhat","public_url":"https:\/\/www.thingiverse.com\/saywhat","thumbnail":"https:\/\/www.thingiverse.com\/img\/default\/avatar\/avatar_default_thumb_medium.jpg"},{"id":15261,"name":"nwk","first_name":"","last_name":"","url":"https:\/\/api.thingiverse.com\/users\/nwk","public_url":"https:\/\/www.thingiverse.com\/nwk","thumbnail":"https:\/\/cdn.thingiverse.com\/renders\/53\/53\/cf\/e1\/36\/photo_display_large_thumb_medium.jpg"},{"id":14403,"name":"sector12","first_name":"Matt","last_name":"Teague","url":"https:\/\/api.thingiverse.com\/users\/sector12","public_url":"https:\/\/www.thingiverse.com\/sector12","thumbnail":"https:\/\/www.thingiverse.com\/img\/default\/avatar\/avatar_default_thumb_medium.jpg"},{"id":12869,"name":"shaji","first_name":"Sharjeel","last_name":"Aziz","url":"https:\/\/api.thingiverse.com\/users\/shaji","public_url":"https:\/\/www.thingiverse.com\/shaji","thumbnail":"https:\/\/cdn.thingiverse.com\/renders\/dc\/87\/3c\/7c\/7c\/IMG_0279_thumb_medium.jpg"},{"id":9885,"name":"tinyenormous","first_name":"","last_name":"","url":"https:\/\/api.thingiverse.com\/users\/tinyenormous","public_url":"https:\/\/www.thingiverse.com\/tinyenormous","thumbnail":"https:\/\/cdn.thingiverse.com\/renders\/8c\/82\/f2\/f5\/31\/Screen_Shot_2012-03-05_at_8.46.16_AM_display_large_thumb_medium.jpg"},{"id":850,"name":"jmil","first_name":"Jordan","last_name":"Miller","url":"https:\/\/api.thingiverse.com\/users\/jmil","public_url":"https:\/\/www.thingiverse.com\/jmil","thumbnail":"https:\/\/cdn.thingiverse.com\/renders\/e3\/0a\/6c\/bd\/29\/photo_display_large_thumb_medium.jpg"},{"id":793,"name":"builttospec","first_name":"Craig","last_name":"Berscheidt","url":"https:\/\/api.thingiverse.com\/users\/builttospec","public_url":"https:\/\/www.thingiverse.com\/builttospec","thumbnail":"https:\/\/cdn.thingiverse.com\/renders\/be\/9a\/6c\/91\/5c\/av-big_display_large_thumb_medium.jpg"},{"id":260,"name":"vonslatt","first_name":"Jake","last_name":"von Slatt","url":"https:\/\/api.thingiverse.com\/users\/vonslatt","public_url":"https:\/\/www.thingiverse.com\/vonslatt","thumbnail":"https:\/\/cdn.thingiverse.com\/renders\/d7\/0f\/da\/df\/b2\/3077770188_862f1984e7_t_display_large_thumb_medium.jpg"},{"id":181,"name":"Erik","first_name":"Erik","last_name":"de Bruijn","url":"https:\/\/api.thingiverse.com\/users\/Erik","public_url":"https:\/\/www.thingiverse.com\/Erik","thumbnail":"https:\/\/cdn.thingiverse.com\/renders\/28\/47\/f6\/93\/14\/IMG_2808_display_large_thumb_medium.jpg"}]