[{"id":51215,"name":"zarflens.stl","size":177282,"url":"https:\/\/api.thingiverse.com\/files\/51215","public_url":"https:\/\/www.thingiverse.com\/download:51215","download_url":"https:\/\/api.thingiverse.com\/files\/51215\/download","threejs_url":"https:\/\/cdn.thingiverse.com\/threejs_json\/e3\/51\/b9\/6c\/8a\/61727439zarflens.js","thumbnail":"https:\/\/thingiverse-rerender-new.s3.amazonaws.com\/renders\/7c\/8a\/9f\/0b\/44\/zarflens_thumb_medium.jpg","default_image":{"id":97479,"url":"https:\/\/cdn.thingiverse.com\/assets\/32\/e9\/54\/92\/1c\/zarflens.stl","name":"zarflens.jpg","sizes":[{"type":"thumb","size":"large","url":"https:\/\/thingiverse-rerender-new.s3.amazonaws.com\/renders\/7c\/8a\/9f\/0b\/44\/zarflens_thumb_large.jpg"},{"type":"thumb","size":"medium","url":"https:\/\/thingiverse-rerender-new.s3.amazonaws.com\/renders\/7c\/8a\/9f\/0b\/44\/zarflens_thumb_medium.jpg"},{"type":"thumb","size":"small","url":"https:\/\/thingiverse-rerender-new.s3.amazonaws.com\/renders\/7c\/8a\/9f\/0b\/44\/zarflens_thumb_small.jpg"},{"type":"thumb","size":"tiny","url":"https:\/\/thingiverse-rerender-new.s3.amazonaws.com\/renders\/7c\/8a\/9f\/0b\/44\/zarflens_thumb_tiny.jpg"},{"type":"preview","size":"featured","url":"https:\/\/thingiverse-rerender-new.s3.amazonaws.com\/renders\/7c\/8a\/9f\/0b\/44\/zarflens_preview_featured.jpg"},{"type":"preview","size":"card","url":"https:\/\/thingiverse-rerender-new.s3.amazonaws.com\/renders\/7c\/8a\/9f\/0b\/44\/zarflens_preview_card.jpg"},{"type":"preview","size":"large","url":"https:\/\/thingiverse-rerender-new.s3.amazonaws.com\/renders\/7c\/8a\/9f\/0b\/44\/zarflens_preview_large.jpg"},{"type":"preview","size":"medium","url":"https:\/\/thingiverse-rerender-new.s3.amazonaws.com\/renders\/7c\/8a\/9f\/0b\/44\/zarflens_preview_medium.jpg"},{"type":"preview","size":"small","url":"https:\/\/thingiverse-rerender-new.s3.amazonaws.com\/renders\/7c\/8a\/9f\/0b\/44\/zarflens_preview_small.jpg"},{"type":"preview","size":"birdwing","url":"https:\/\/thingiverse-rerender-new.s3.amazonaws.com\/renders\/7c\/8a\/9f\/0b\/44\/zarflens.jpg"},{"type":"preview","size":"tiny","url":"https:\/\/thingiverse-rerender-new.s3.amazonaws.com\/renders\/7c\/8a\/9f\/0b\/44\/zarflens_preview_tiny.jpg"},{"type":"preview","size":"tinycard","url":"https:\/\/thingiverse-rerender-new.s3.amazonaws.com\/renders\/7c\/8a\/9f\/0b\/44\/zarflens_preview_tinycard.jpg"},{"type":"display","size":"large","url":"https:\/\/thingiverse-rerender-new.s3.amazonaws.com\/renders\/7c\/8a\/9f\/0b\/44\/zarflens_display_large.jpg"},{"type":"display","size":"medium","url":"https:\/\/thingiverse-rerender-new.s3.amazonaws.com\/renders\/7c\/8a\/9f\/0b\/44\/zarflens_display_medium.jpg"},{"type":"display","size":"small","url":"https:\/\/thingiverse-rerender-new.s3.amazonaws.com\/renders\/7c\/8a\/9f\/0b\/44\/zarflens_display_small.jpg"}],"added":"2012-07-27T07:41:45+00:00"},"date":"2012-01-06 18:11:46","formatted_size":"173 kb","meta_data":[]}]