[{"id":1229050,"name":"Msync","first_name":"Beka","last_name":"Clary","url":"https:\/\/api.thingiverse.com\/users\/Msync","public_url":"https:\/\/www.thingiverse.com\/Msync","thumbnail":"https:\/\/www.thingiverse.com\/img\/default\/avatar\/avatar_default_thumb_medium.jpg"},{"id":824322,"name":"SergioZGZ","first_name":"Sergio","last_name":"Calvo Ena","url":"https:\/\/api.thingiverse.com\/users\/SergioZGZ","public_url":"https:\/\/www.thingiverse.com\/SergioZGZ","thumbnail":"https:\/\/www.thingiverse.com\/img\/default\/avatar\/avatar_default_thumb_medium.jpg"},{"id":344717,"name":"PersonalDrones","first_name":"Personal","last_name":"Drones","url":"https:\/\/api.thingiverse.com\/users\/PersonalDrones","public_url":"https:\/\/www.thingiverse.com\/PersonalDrones","thumbnail":"https:\/\/cdn.thingiverse.com\/renders\/8e\/61\/92\/da\/f5\/Personal_Drones_squarextwitter-100x100_thumb_medium.jpg"},{"id":1075085,"name":"gabriela78","first_name":"Gribis","last_name":"Gabriela","url":"https:\/\/api.thingiverse.com\/users\/gabriela78","public_url":"https:\/\/www.thingiverse.com\/gabriela78","thumbnail":"https:\/\/www.thingiverse.com\/img\/default\/avatar\/avatar_default_thumb_medium.jpg"},{"id":1142935,"name":"andreas_ulrich","first_name":"Andreas","last_name":"Ulrich","url":"https:\/\/api.thingiverse.com\/users\/andreas_ulrich","public_url":"https:\/\/www.thingiverse.com\/andreas_ulrich","thumbnail":"https:\/\/www.thingiverse.com\/img\/default\/avatar\/avatar_default_thumb_medium.jpg"},{"id":1000141,"name":"druhisethi","first_name":"Druhi","last_name":"Sethi","url":"https:\/\/api.thingiverse.com\/users\/druhisethi","public_url":"https:\/\/www.thingiverse.com\/druhisethi","thumbnail":"https:\/\/www.thingiverse.com\/img\/default\/avatar\/avatar_default_thumb_medium.jpg"},{"id":147826,"name":"RoseLily_Garden","first_name":"Tony","last_name":"Emmi","url":"https:\/\/api.thingiverse.com\/users\/RoseLily_Garden","public_url":"https:\/\/www.thingiverse.com\/RoseLily_Garden","thumbnail":"https:\/\/cdn.thingiverse.com\/renders\/7c\/3f\/9a\/e1\/49\/image_thumb_medium.jpg"},{"id":968254,"name":"keithp00ps","first_name":"Keith","last_name":"Evans","url":"https:\/\/api.thingiverse.com\/users\/keithp00ps","public_url":"https:\/\/www.thingiverse.com\/keithp00ps","thumbnail":"https:\/\/www.thingiverse.com\/img\/default\/avatar\/avatar_default_thumb_medium.jpg"},{"id":960348,"name":"Sapphirebaby","first_name":"Katie","last_name":"Byler","url":"https:\/\/api.thingiverse.com\/users\/Sapphirebaby","public_url":"https:\/\/www.thingiverse.com\/Sapphirebaby","thumbnail":"https:\/\/www.thingiverse.com\/img\/default\/avatar\/avatar_default_thumb_medium.jpg"},{"id":872653,"name":"SpaceCore2000","first_name":"Robert","last_name":"Blahm-Green","url":"https:\/\/api.thingiverse.com\/users\/SpaceCore2000","public_url":"https:\/\/www.thingiverse.com\/SpaceCore2000","thumbnail":"https:\/\/www.thingiverse.com\/img\/default\/avatar\/avatar_default_thumb_medium.jpg"},{"id":95253,"name":"hansena","first_name":"","last_name":"","url":"https:\/\/api.thingiverse.com\/users\/hansena","public_url":"https:\/\/www.thingiverse.com\/hansena","thumbnail":"https:\/\/cdn.thingiverse.com\/renders\/80\/6c\/46\/6a\/b1\/alaska_asce_8_thumb_medium.jpg"},{"id":956172,"name":"Ihavearaccoonfact","first_name":"Emily","last_name":"Dawson","url":"https:\/\/api.thingiverse.com\/users\/Ihavearaccoonfact","public_url":"https:\/\/www.thingiverse.com\/Ihavearaccoonfact","thumbnail":"https:\/\/www.thingiverse.com\/img\/default\/avatar\/avatar_default_thumb_medium.jpg"},{"id":914810,"name":"nineismine","first_name":"chad","last_name":"torkkola","url":"https:\/\/api.thingiverse.com\/users\/nineismine","public_url":"https:\/\/www.thingiverse.com\/nineismine","thumbnail":"https:\/\/www.thingiverse.com\/img\/default\/avatar\/avatar_default_thumb_medium.jpg"},{"id":953345,"name":"AZDawg","first_name":"Steve","last_name":"Gotthardt","url":"https:\/\/api.thingiverse.com\/users\/AZDawg","public_url":"https:\/\/www.thingiverse.com\/AZDawg","thumbnail":"https:\/\/cdn.thingiverse.com\/renders\/17\/3e\/8a\/5d\/56\/ec0d6afb8c370157f605a79b238cc294_thumb_medium.jpg"},{"id":838913,"name":"TubetasticPimps","first_name":"Sarah","last_name":"Smith","url":"https:\/\/api.thingiverse.com\/users\/TubetasticPimps","public_url":"https:\/\/www.thingiverse.com\/TubetasticPimps","thumbnail":"https:\/\/www.thingiverse.com\/img\/default\/avatar\/avatar_default_thumb_medium.jpg"},{"id":946363,"name":"microled","first_name":"","last_name":"","url":"https:\/\/api.thingiverse.com\/users\/microled","public_url":"https:\/\/www.thingiverse.com\/microled","thumbnail":"https:\/\/www.thingiverse.com\/img\/default\/avatar\/avatar_default_thumb_medium.jpg"},{"id":911507,"name":"cheeoh","first_name":"Chi","last_name":"Ho","url":"https:\/\/api.thingiverse.com\/users\/cheeoh","public_url":"https:\/\/www.thingiverse.com\/cheeoh","thumbnail":"https:\/\/www.thingiverse.com\/img\/default\/avatar\/avatar_default_thumb_medium.jpg"},{"id":819540,"name":"pinoy4065","first_name":"Andrew","last_name":"","url":"https:\/\/api.thingiverse.com\/users\/pinoy4065","public_url":"https:\/\/www.thingiverse.com\/pinoy4065","thumbnail":"https:\/\/www.thingiverse.com\/img\/default\/avatar\/avatar_default_thumb_medium.jpg"},{"id":786697,"name":"Kharr","first_name":"Kharr","last_name":"DUDDLE","url":"https:\/\/api.thingiverse.com\/users\/Kharr","public_url":"https:\/\/www.thingiverse.com\/Kharr","thumbnail":"https:\/\/cdn.thingiverse.com\/renders\/a8\/b1\/6f\/95\/6d\/8e1e39ba3c443e415d22e2f69b4a4122_thumb_medium.JPG"},{"id":818622,"name":"SnapCracklePrint","first_name":"Jack","last_name":"Andrews","url":"https:\/\/api.thingiverse.com\/users\/SnapCracklePrint","public_url":"https:\/\/www.thingiverse.com\/SnapCracklePrint","thumbnail":"https:\/\/www.thingiverse.com\/img\/default\/avatar\/avatar_default_thumb_medium.jpg"},{"id":853417,"name":"Emrobison","first_name":"Elisabeth","last_name":"Robison","url":"https:\/\/api.thingiverse.com\/users\/Emrobison","public_url":"https:\/\/www.thingiverse.com\/Emrobison","thumbnail":"https:\/\/www.thingiverse.com\/img\/default\/avatar\/avatar_default_thumb_medium.jpg"},{"id":293182,"name":"RonnieBlaze","first_name":"Ron","last_name":"Rolfes","url":"https:\/\/api.thingiverse.com\/users\/RonnieBlaze","public_url":"https:\/\/www.thingiverse.com\/RonnieBlaze","thumbnail":"https:\/\/www.thingiverse.com\/img\/default\/avatar\/avatar_default_thumb_medium.jpg"},{"id":882734,"name":"tinaw","first_name":"Tina","last_name":"Wiman","url":"https:\/\/api.thingiverse.com\/users\/tinaw","public_url":"https:\/\/www.thingiverse.com\/tinaw","thumbnail":"https:\/\/cdn.thingiverse.com\/renders\/90\/08\/ea\/3c\/d4\/caa16aab45d2e0fa3a051e344c1c2efe_thumb_medium.jpg"},{"id":875477,"name":"Zannon","first_name":"Alexandre","last_name":"Zannon","url":"https:\/\/api.thingiverse.com\/users\/Zannon","public_url":"https:\/\/www.thingiverse.com\/Zannon","thumbnail":"https:\/\/www.thingiverse.com\/img\/default\/avatar\/avatar_default_thumb_medium.jpg"},{"id":852156,"name":"Daphotosmedia","first_name":"Daphne","last_name":"Hecko","url":"https:\/\/api.thingiverse.com\/users\/Daphotosmedia","public_url":"https:\/\/www.thingiverse.com\/Daphotosmedia","thumbnail":"https:\/\/cdn.thingiverse.com\/renders\/d9\/05\/00\/34\/09\/9f360c5ab7736510df54c882e9dbf188_thumb_medium.jpeg"},{"id":479023,"name":"Mario74","first_name":"Mario","last_name":"Russo","url":"https:\/\/api.thingiverse.com\/users\/Mario74","public_url":"https:\/\/www.thingiverse.com\/Mario74","thumbnail":"https:\/\/www.thingiverse.com\/img\/default\/avatar\/avatar_default_thumb_medium.jpg"},{"id":892546,"name":"Hannahcs","first_name":"Hannah","last_name":"Saboune","url":"https:\/\/api.thingiverse.com\/users\/Hannahcs","public_url":"https:\/\/www.thingiverse.com\/Hannahcs","thumbnail":"https:\/\/www.thingiverse.com\/img\/default\/avatar\/avatar_default_thumb_medium.jpg"},{"id":840860,"name":"tomo1110","first_name":"\u670b\u5178","last_name":"\u5ddd\u53e3","url":"https:\/\/api.thingiverse.com\/users\/tomo1110","public_url":"https:\/\/www.thingiverse.com\/tomo1110","thumbnail":"https:\/\/www.thingiverse.com\/img\/default\/avatar\/avatar_maker_thumb_medium.jpg"},{"id":795769,"name":"misse888","first_name":"Man","last_name":"yoyo","url":"https:\/\/api.thingiverse.com\/users\/misse888","public_url":"https:\/\/www.thingiverse.com\/misse888","thumbnail":"https:\/\/www.thingiverse.com\/img\/default\/avatar\/avatar_default_thumb_medium.jpg"},{"id":841873,"name":"peachpellen","first_name":"Peach","last_name":"Pellen","url":"https:\/\/api.thingiverse.com\/users\/peachpellen","public_url":"https:\/\/www.thingiverse.com\/peachpellen","thumbnail":"https:\/\/cdn.thingiverse.com\/renders\/1e\/a8\/91\/25\/a9\/54578611656798245210940077c32ced_thumb_medium.jpg"},{"id":615375,"name":"Minkaxyz","first_name":"Hans","last_name":"Werwolf","url":"https:\/\/api.thingiverse.com\/users\/Minkaxyz","public_url":"https:\/\/www.thingiverse.com\/Minkaxyz","thumbnail":"https:\/\/www.thingiverse.com\/img\/default\/avatar\/avatar_default_thumb_medium.jpg"},{"id":839484,"name":"Darkreaper10","first_name":"Peet","last_name":"Esterhuizen","url":"https:\/\/api.thingiverse.com\/users\/Darkreaper10","public_url":"https:\/\/www.thingiverse.com\/Darkreaper10","thumbnail":"https:\/\/cdn.thingiverse.com\/renders\/c9\/37\/09\/62\/05\/5763e44137f372e3908af1c186d4bb1b_thumb_medium.jpg"},{"id":651022,"name":"jpgall","first_name":"Jean Pierre","last_name":"Gall","url":"https:\/\/api.thingiverse.com\/users\/jpgall","public_url":"https:\/\/www.thingiverse.com\/jpgall","thumbnail":"https:\/\/www.thingiverse.com\/img\/default\/avatar\/avatar_engineer_thumb_medium.jpg"},{"id":845554,"name":"slothpc","first_name":"anthony","last_name":"Kelley","url":"https:\/\/api.thingiverse.com\/users\/slothpc","public_url":"https:\/\/www.thingiverse.com\/slothpc","thumbnail":"https:\/\/www.thingiverse.com\/img\/default\/avatar\/avatar_default_thumb_medium.jpg"},{"id":735440,"name":"sertoes","first_name":"Prenom","last_name":"Nom","url":"https:\/\/api.thingiverse.com\/users\/sertoes","public_url":"https:\/\/www.thingiverse.com\/sertoes","thumbnail":"https:\/\/www.thingiverse.com\/img\/default\/avatar\/avatar_default_thumb_medium.jpg"},{"id":397004,"name":"dasistdaniel","first_name":"Daniel","last_name":"Intrup","url":"https:\/\/api.thingiverse.com\/users\/dasistdaniel","public_url":"https:\/\/www.thingiverse.com\/dasistdaniel","thumbnail":"https:\/\/www.thingiverse.com\/img\/default\/avatar\/avatar_default_thumb_medium.jpg"},{"id":775711,"name":"kimshobe","first_name":"kim","last_name":"shobe","url":"https:\/\/api.thingiverse.com\/users\/kimshobe","public_url":"https:\/\/www.thingiverse.com\/kimshobe","thumbnail":"https:\/\/www.thingiverse.com\/img\/default\/avatar\/avatar_default_thumb_medium.jpg"},{"id":146615,"name":"jakubprusa","first_name":"","last_name":"","url":"https:\/\/api.thingiverse.com\/users\/jakubprusa","public_url":"https:\/\/www.thingiverse.com\/jakubprusa","thumbnail":"https:\/\/www.thingiverse.com\/img\/default\/avatar\/avatar_default_thumb_medium.jpg"},{"id":786690,"name":"vectality","first_name":"Matt","last_name":"Conwell","url":"https:\/\/api.thingiverse.com\/users\/vectality","public_url":"https:\/\/www.thingiverse.com\/vectality","thumbnail":"https:\/\/cdn.thingiverse.com\/renders\/e7\/07\/2f\/db\/bf\/59743a8a97a17a9212ee6d2d9b81f5d6_thumb_medium.jpg"},{"id":575276,"name":"lurkus","first_name":"CJ","last_name":"Alcorta","url":"https:\/\/api.thingiverse.com\/users\/lurkus","public_url":"https:\/\/www.thingiverse.com\/lurkus","thumbnail":"https:\/\/www.thingiverse.com\/img\/default\/avatar\/avatar_default_thumb_medium.jpg"},{"id":780266,"name":"M21tekalu","first_name":"Teani","last_name":"Kaluhikaua","url":"https:\/\/api.thingiverse.com\/users\/M21tekalu","public_url":"https:\/\/www.thingiverse.com\/M21tekalu","thumbnail":"https:\/\/cdn.thingiverse.com\/renders\/00\/42\/be\/fb\/42\/7a74a40d93145739c8703f6e23a607b2_thumb_medium.jpg"},{"id":323262,"name":"tootooni","first_name":"Samie","last_name":"Tootooni","url":"https:\/\/api.thingiverse.com\/users\/tootooni","public_url":"https:\/\/www.thingiverse.com\/tootooni","thumbnail":"https:\/\/www.thingiverse.com\/img\/default\/avatar\/avatar_default_thumb_medium.jpg"},{"id":366937,"name":"IndyMaker","first_name":"Steve","last_name":"Prifogle","url":"https:\/\/api.thingiverse.com\/users\/IndyMaker","public_url":"https:\/\/www.thingiverse.com\/IndyMaker","thumbnail":"https:\/\/www.thingiverse.com\/img\/default\/avatar\/avatar_engineer_thumb_medium.jpg"},{"id":743500,"name":"mgasperi","first_name":"Maurizio","last_name":"Gasperi","url":"https:\/\/api.thingiverse.com\/users\/mgasperi","public_url":"https:\/\/www.thingiverse.com\/mgasperi","thumbnail":"https:\/\/www.thingiverse.com\/img\/default\/avatar\/avatar_maker_thumb_medium.jpg"},{"id":693248,"name":"xchased","first_name":"xchased","last_name":" ","url":"https:\/\/api.thingiverse.com\/users\/xchased","public_url":"https:\/\/www.thingiverse.com\/xchased","thumbnail":"https:\/\/www.thingiverse.com\/img\/default\/avatar\/avatar_default_thumb_medium.jpg"},{"id":442815,"name":"Eezitec","first_name":"Mitchel","last_name":"Dumlao","url":"https:\/\/api.thingiverse.com\/users\/Eezitec","public_url":"https:\/\/www.thingiverse.com\/Eezitec","thumbnail":"https:\/\/cdn.thingiverse.com\/renders\/2e\/7e\/e7\/d9\/10\/dc4a247b2a4c1f22effd8875703bfbb1_thumb_medium.jpg"},{"id":448409,"name":"schwertfische","first_name":"Esteban","last_name":"Lopez A","url":"https:\/\/api.thingiverse.com\/users\/schwertfische","public_url":"https:\/\/www.thingiverse.com\/schwertfische","thumbnail":"https:\/\/cdn.thingiverse.com\/renders\/a8\/c3\/0e\/0c\/c4\/20150207_143820%5B1%5D_thumb_medium.jpg"},{"id":326181,"name":"simonebenatti","first_name":"Simone","last_name":"Benatti","url":"https:\/\/api.thingiverse.com\/users\/simonebenatti","public_url":"https:\/\/www.thingiverse.com\/simonebenatti","thumbnail":"https:\/\/cdn.thingiverse.com\/renders\/5b\/7c\/6d\/37\/41\/5895_119879141273_117846756273_2510348_382773_n_thumb_medium.jpg"},{"id":478944,"name":"Mokaha51","first_name":"Sandro","last_name":"Moka","url":"https:\/\/api.thingiverse.com\/users\/Mokaha51","public_url":"https:\/\/www.thingiverse.com\/Mokaha51","thumbnail":"https:\/\/www.thingiverse.com\/img\/default\/avatar\/avatar_default_thumb_medium.jpg"},{"id":623443,"name":"zaqpoi","first_name":"zaq","last_name":"poi","url":"https:\/\/api.thingiverse.com\/users\/zaqpoi","public_url":"https:\/\/www.thingiverse.com\/zaqpoi","thumbnail":"https:\/\/www.thingiverse.com\/img\/default\/avatar\/avatar_default_thumb_medium.jpg"},{"id":744349,"name":"jufelix","first_name":"Juliana","last_name":"Felix","url":"https:\/\/api.thingiverse.com\/users\/jufelix","public_url":"https:\/\/www.thingiverse.com\/jufelix","thumbnail":"https:\/\/www.thingiverse.com\/img\/default\/avatar\/avatar_default_thumb_medium.jpg"},{"id":737003,"name":"thiagomiyaguchi","first_name":"Thiago","last_name":"Miyaguchi","url":"https:\/\/api.thingiverse.com\/users\/thiagomiyaguchi","public_url":"https:\/\/www.thingiverse.com\/thiagomiyaguchi","thumbnail":"https:\/\/www.thingiverse.com\/img\/default\/avatar\/avatar_engineer_thumb_medium.jpg"},{"id":515989,"name":"RafaelEstevam","first_name":"RAFAEL","last_name":"ESTEVAM","url":"https:\/\/api.thingiverse.com\/users\/RafaelEstevam","public_url":"https:\/\/www.thingiverse.com\/RafaelEstevam","thumbnail":"https:\/\/www.thingiverse.com\/img\/default\/avatar\/avatar_default_thumb_medium.jpg"},{"id":466901,"name":"bocken","first_name":"conny","last_name":"andersson","url":"https:\/\/api.thingiverse.com\/users\/bocken","public_url":"https:\/\/www.thingiverse.com\/bocken","thumbnail":"https:\/\/cdn.thingiverse.com\/renders\/57\/b5\/e7\/2a\/3f\/d2b5ca33bd970f64a6301fa75ae2eb22_thumb_medium.jpg"},{"id":718130,"name":"dominicjprice","first_name":"Dominic","last_name":"Price","url":"https:\/\/api.thingiverse.com\/users\/dominicjprice","public_url":"https:\/\/www.thingiverse.com\/dominicjprice","thumbnail":"https:\/\/www.thingiverse.com\/img\/default\/avatar\/avatar_default_thumb_medium.jpg"},{"id":735600,"name":"mobapo","first_name":"Mois\u00e9s","last_name":"Batista","url":"https:\/\/api.thingiverse.com\/users\/mobapo","public_url":"https:\/\/www.thingiverse.com\/mobapo","thumbnail":"https:\/\/www.thingiverse.com\/img\/default\/avatar\/avatar_default_thumb_medium.jpg"},{"id":731384,"name":"Clem_V","first_name":"Cl\u00e9ment","last_name":"VERGER","url":"https:\/\/api.thingiverse.com\/users\/Clem_V","public_url":"https:\/\/www.thingiverse.com\/Clem_V","thumbnail":"https:\/\/cdn.thingiverse.com\/renders\/fe\/ab\/1c\/93\/cb\/54578611656798245210940077c32ced_thumb_medium.jpg"},{"id":42052,"name":"faisalomar","first_name":"","last_name":"","url":"https:\/\/api.thingiverse.com\/users\/faisalomar","public_url":"https:\/\/www.thingiverse.com\/faisalomar","thumbnail":"https:\/\/cdn.thingiverse.com\/renders\/57\/36\/33\/8a\/e2\/IMG00104-20120809-1320_thumb_medium.jpg"},{"id":705961,"name":"jcarlosn","first_name":"joca","last_name":"lol","url":"https:\/\/api.thingiverse.com\/users\/jcarlosn","public_url":"https:\/\/www.thingiverse.com\/jcarlosn","thumbnail":"https:\/\/www.thingiverse.com\/img\/default\/avatar\/avatar_default_thumb_medium.jpg"},{"id":632195,"name":"StillNotARobot","first_name":"David","last_name":"Andrews","url":"https:\/\/api.thingiverse.com\/users\/StillNotARobot","public_url":"https:\/\/www.thingiverse.com\/StillNotARobot","thumbnail":"https:\/\/www.thingiverse.com\/img\/default\/avatar\/avatar_maker_thumb_medium.jpg"},{"id":655875,"name":"poop15","first_name":"michael","last_name":"segan","url":"https:\/\/api.thingiverse.com\/users\/poop15","public_url":"https:\/\/www.thingiverse.com\/poop15","thumbnail":"https:\/\/cdn.thingiverse.com\/renders\/7d\/11\/91\/b9\/3d\/Hero_Halo5_thumb_medium.jpg"},{"id":600776,"name":"Vasconnesso74","first_name":"Pierpaolo","last_name":"Forciniti","url":"https:\/\/api.thingiverse.com\/users\/Vasconnesso74","public_url":"https:\/\/www.thingiverse.com\/Vasconnesso74","thumbnail":"https:\/\/cdn.thingiverse.com\/renders\/bd\/3c\/8a\/fe\/68\/IMG_5559_thumb_medium.JPG"},{"id":461411,"name":"UnNamedGER","first_name":"enok","last_name":"aneggi","url":"https:\/\/api.thingiverse.com\/users\/UnNamedGER","public_url":"https:\/\/www.thingiverse.com\/UnNamedGER","thumbnail":"https:\/\/www.thingiverse.com\/img\/default\/avatar\/avatar_default_thumb_medium.jpg"},{"id":706261,"name":"HnBrailroad","first_name":"Harry","last_name":"Jackson","url":"https:\/\/api.thingiverse.com\/users\/HnBrailroad","public_url":"https:\/\/www.thingiverse.com\/HnBrailroad","thumbnail":"https:\/\/www.thingiverse.com\/img\/default\/avatar\/avatar_default_thumb_medium.jpg"},{"id":645262,"name":"MarauderX","first_name":"Mara","last_name":"UderX","url":"https:\/\/api.thingiverse.com\/users\/MarauderX","public_url":"https:\/\/www.thingiverse.com\/MarauderX","thumbnail":"https:\/\/cdn.thingiverse.com\/renders\/23\/c9\/e3\/91\/25\/LorienFull2_thumb_medium.jpg"},{"id":396781,"name":"G2K","first_name":"Andre","last_name":"Khoury","url":"https:\/\/api.thingiverse.com\/users\/G2K","public_url":"https:\/\/www.thingiverse.com\/G2K","thumbnail":"https:\/\/www.thingiverse.com\/img\/default\/avatar\/avatar_default_thumb_medium.jpg"},{"id":551738,"name":"willdgf","first_name":"Josh","last_name":"Will","url":"https:\/\/api.thingiverse.com\/users\/willdgf","public_url":"https:\/\/www.thingiverse.com\/willdgf","thumbnail":"https:\/\/cdn.thingiverse.com\/renders\/11\/b1\/bf\/73\/57\/What_was_that_thumb_medium.jpg"},{"id":220914,"name":"reBoot185","first_name":"Joshua (otamusima)","last_name":"King (sabadunia)","url":"https:\/\/api.thingiverse.com\/users\/reBoot185","public_url":"https:\/\/www.thingiverse.com\/reBoot185","thumbnail":"https:\/\/cdn.thingiverse.com\/renders\/86\/67\/86\/bf\/79\/c3aef55f1c6a74ff4978967a9bfa67da_thumb_medium.jpg"},{"id":684968,"name":"kaitlyn6584","first_name":"katie","last_name":"6584","url":"https:\/\/api.thingiverse.com\/users\/kaitlyn6584","public_url":"https:\/\/www.thingiverse.com\/kaitlyn6584","thumbnail":"https:\/\/www.thingiverse.com\/img\/default\/avatar\/avatar_default_thumb_medium.jpg"},{"id":622660,"name":"Bugabbott","first_name":"Carleigh","last_name":"Abbott","url":"https:\/\/api.thingiverse.com\/users\/Bugabbott","public_url":"https:\/\/www.thingiverse.com\/Bugabbott","thumbnail":"https:\/\/www.thingiverse.com\/img\/default\/avatar\/avatar_default_thumb_medium.jpg"},{"id":355105,"name":"samhinsh","first_name":"Samuel","last_name":"Hinshelwood","url":"https:\/\/api.thingiverse.com\/users\/samhinsh","public_url":"https:\/\/www.thingiverse.com\/samhinsh","thumbnail":"https:\/\/www.thingiverse.com\/img\/default\/avatar\/avatar_engineer_thumb_medium.jpg"},{"id":613763,"name":"fsantibanezleal","first_name":"Felipe","last_name":"Santib\u00e1\u00f1ez Leal","url":"https:\/\/api.thingiverse.com\/users\/fsantibanezleal","public_url":"https:\/\/www.thingiverse.com\/fsantibanezleal","thumbnail":"https:\/\/cdn.thingiverse.com\/renders\/81\/4f\/bc\/eb\/bf\/2015-06-144_thumb_medium.jpg"},{"id":590753,"name":"timothybs","first_name":"Timothy","last_name":"Sumner","url":"https:\/\/api.thingiverse.com\/users\/timothybs","public_url":"https:\/\/www.thingiverse.com\/timothybs","thumbnail":"https:\/\/www.thingiverse.com\/img\/default\/avatar\/avatar_default_thumb_medium.jpg"},{"id":412940,"name":"donttouchmyfork","first_name":"Tom","last_name":"Moore","url":"https:\/\/api.thingiverse.com\/users\/donttouchmyfork","public_url":"https:\/\/www.thingiverse.com\/donttouchmyfork","thumbnail":"https:\/\/cdn.thingiverse.com\/renders\/89\/c6\/ff\/c5\/5b\/Me_%282%29_thumb_medium.jpg"},{"id":143336,"name":"Double_Helix","first_name":"","last_name":"","url":"https:\/\/api.thingiverse.com\/users\/Double_Helix","public_url":"https:\/\/www.thingiverse.com\/Double_Helix","thumbnail":"https:\/\/cdn.thingiverse.com\/renders\/55\/f3\/fb\/d6\/55\/4Lstickerdoublehelix2_thumb_medium.jpg"},{"id":451081,"name":"algan","first_name":"Albert","last_name":"Gan","url":"https:\/\/api.thingiverse.com\/users\/algan","public_url":"https:\/\/www.thingiverse.com\/algan","thumbnail":"https:\/\/www.thingiverse.com\/img\/default\/avatar\/avatar_default_thumb_medium.jpg"},{"id":478825,"name":"happy12321","first_name":"happy","last_name":"rain","url":"https:\/\/api.thingiverse.com\/users\/happy12321","public_url":"https:\/\/www.thingiverse.com\/happy12321","thumbnail":"https:\/\/www.thingiverse.com\/img\/default\/avatar\/avatar_student_thumb_medium.jpg"},{"id":462067,"name":"jg210302","first_name":"Jeremy","last_name":"Gillum","url":"https:\/\/api.thingiverse.com\/users\/jg210302","public_url":"https:\/\/www.thingiverse.com\/jg210302","thumbnail":"https:\/\/www.thingiverse.com\/img\/default\/avatar\/avatar_engineer_thumb_medium.jpg"},{"id":336867,"name":"corwellcustoms","first_name":"Corwell","last_name":"Customs","url":"https:\/\/api.thingiverse.com\/users\/corwellcustoms","public_url":"https:\/\/www.thingiverse.com\/corwellcustoms","thumbnail":"https:\/\/cdn.thingiverse.com\/renders\/ec\/1b\/d1\/5e\/0e\/10273558_681643031894530_8374937161630347052_n_thumb_medium.jpg"},{"id":319413,"name":"Ptnpowers","first_name":"Patrick","last_name":"Powers","url":"https:\/\/api.thingiverse.com\/users\/Ptnpowers","public_url":"https:\/\/www.thingiverse.com\/Ptnpowers","thumbnail":"https:\/\/cdn.thingiverse.com\/renders\/71\/85\/72\/b0\/09\/20140505_154547_thumb_medium.jpg"},{"id":422682,"name":"muuhoffman","first_name":"Matt","last_name":"Hoffman","url":"https:\/\/api.thingiverse.com\/users\/muuhoffman","public_url":"https:\/\/www.thingiverse.com\/muuhoffman","thumbnail":"https:\/\/www.thingiverse.com\/img\/default\/avatar\/avatar_default_thumb_medium.jpg"},{"id":406280,"name":"Mazzi827","first_name":"Melissa","last_name":"Tesei","url":"https:\/\/api.thingiverse.com\/users\/Mazzi827","public_url":"https:\/\/www.thingiverse.com\/Mazzi827","thumbnail":"https:\/\/cdn.thingiverse.com\/renders\/be\/72\/e8\/44\/9e\/image_thumb_medium.jpg"},{"id":225450,"name":"huangppo","first_name":"Lord","last_name":"Hsu","url":"https:\/\/api.thingiverse.com\/users\/huangppo","public_url":"https:\/\/www.thingiverse.com\/huangppo","thumbnail":"https:\/\/www.thingiverse.com\/img\/default\/avatar\/avatar_default_thumb_medium.jpg"},{"id":354261,"name":"RudyPJ_83","first_name":"Rudney","last_name":"Patrick","url":"https:\/\/api.thingiverse.com\/users\/RudyPJ_83","public_url":"https:\/\/www.thingiverse.com\/RudyPJ_83","thumbnail":"https:\/\/cdn.thingiverse.com\/renders\/04\/37\/62\/be\/95\/Meu_instantneo_2_thumb_medium.jpg"},{"id":13830,"name":"imrahil","first_name":"Jarek","last_name":"Szczepanski","url":"https:\/\/api.thingiverse.com\/users\/imrahil","public_url":"https:\/\/www.thingiverse.com\/imrahil","thumbnail":"https:\/\/cdn.thingiverse.com\/renders\/96\/f4\/7c\/25\/40\/avatar5_display_large_thumb_medium.jpg"},{"id":302305,"name":"cly10002","first_name":"ccc","last_name":"cccc","url":"https:\/\/api.thingiverse.com\/users\/cly10002","public_url":"https:\/\/www.thingiverse.com\/cly10002","thumbnail":"https:\/\/www.thingiverse.com\/img\/default\/avatar\/avatar_default_thumb_medium.jpg"},{"id":345566,"name":"xychose","first_name":"Josef","last_name":"Nov","url":"https:\/\/api.thingiverse.com\/users\/xychose","public_url":"https:\/\/www.thingiverse.com\/xychose","thumbnail":"https:\/\/www.thingiverse.com\/img\/default\/avatar\/avatar_engineer_thumb_medium.jpg"},{"id":299159,"name":"HYKGOML","first_name":"James","last_name":"Hukill","url":"https:\/\/api.thingiverse.com\/users\/HYKGOML","public_url":"https:\/\/www.thingiverse.com\/HYKGOML","thumbnail":"https:\/\/cdn.thingiverse.com\/renders\/f6\/da\/60\/23\/45\/021e25b4d2d36b8bf10a288f674b30c8_thumb_medium.JPG"},{"id":297835,"name":"usa3dstore","first_name":"Pather","last_name":"Neff","url":"https:\/\/api.thingiverse.com\/users\/usa3dstore","public_url":"https:\/\/www.thingiverse.com\/usa3dstore","thumbnail":"https:\/\/www.thingiverse.com\/img\/default\/avatar\/avatar_default_thumb_medium.jpg"},{"id":323790,"name":"nchlcooper","first_name":"Nichole","last_name":"Cooper","url":"https:\/\/api.thingiverse.com\/users\/nchlcooper","public_url":"https:\/\/www.thingiverse.com\/nchlcooper","thumbnail":"https:\/\/www.thingiverse.com\/img\/default\/avatar\/avatar_default_thumb_medium.jpg"},{"id":238142,"name":"reesy","first_name":"clarisse","last_name":"drake","url":"https:\/\/api.thingiverse.com\/users\/reesy","public_url":"https:\/\/www.thingiverse.com\/reesy","thumbnail":"https:\/\/cdn.thingiverse.com\/renders\/48\/df\/3f\/17\/f8\/justice_thumb_medium.jpg"},{"id":278112,"name":"chudoski","first_name":"Andres","last_name":"Lopez","url":"https:\/\/api.thingiverse.com\/users\/chudoski","public_url":"https:\/\/www.thingiverse.com\/chudoski","thumbnail":"https:\/\/www.thingiverse.com\/img\/default\/avatar\/avatar_default_thumb_medium.jpg"},{"id":255229,"name":"makerfra","first_name":"Francesco","last_name":"Conoscenti","url":"https:\/\/api.thingiverse.com\/users\/makerfra","public_url":"https:\/\/www.thingiverse.com\/makerfra","thumbnail":"https:\/\/www.thingiverse.com\/img\/default\/avatar\/avatar_default_thumb_medium.jpg"},{"id":257518,"name":"blowrance99","first_name":"Betty","last_name":"Lowrance","url":"https:\/\/api.thingiverse.com\/users\/blowrance99","public_url":"https:\/\/www.thingiverse.com\/blowrance99","thumbnail":"https:\/\/www.thingiverse.com\/img\/default\/avatar\/avatar_default_thumb_medium.jpg"},{"id":170293,"name":"Quickbeam","first_name":"Travis","last_name":"Bills","url":"https:\/\/api.thingiverse.com\/users\/Quickbeam","public_url":"https:\/\/www.thingiverse.com\/Quickbeam","thumbnail":"https:\/\/cdn.thingiverse.com\/renders\/c9\/8d\/dc\/ed\/02\/100_0988_thumb_medium.jpg"},{"id":242293,"name":"kaomega","first_name":"Kaleb","last_name":"Harris","url":"https:\/\/api.thingiverse.com\/users\/kaomega","public_url":"https:\/\/www.thingiverse.com\/kaomega","thumbnail":"https:\/\/www.thingiverse.com\/img\/default\/avatar\/avatar_default_thumb_medium.jpg"},{"id":93541,"name":"jsook724","first_name":"","last_name":"","url":"https:\/\/api.thingiverse.com\/users\/jsook724","public_url":"https:\/\/www.thingiverse.com\/jsook724","thumbnail":"https:\/\/www.thingiverse.com\/img\/default\/avatar\/avatar_default_thumb_medium.jpg"},{"id":197667,"name":"calli","first_name":"Carsten","last_name":"Wartmann","url":"https:\/\/api.thingiverse.com\/users\/calli","public_url":"https:\/\/www.thingiverse.com\/calli","thumbnail":"https:\/\/cdn.thingiverse.com\/renders\/4e\/dc\/08\/bc\/e5\/HuhnClay_AvatarTV_thumb_medium.jpg"},{"id":121850,"name":"3dreamfab","first_name":"","last_name":"","url":"https:\/\/api.thingiverse.com\/users\/3dreamfab","public_url":"https:\/\/www.thingiverse.com\/3dreamfab","thumbnail":"https:\/\/www.thingiverse.com\/img\/default\/avatar\/avatar_default_thumb_medium.jpg"},{"id":149817,"name":"davidnorman314","first_name":"David","last_name":"Norman","url":"https:\/\/api.thingiverse.com\/users\/davidnorman314","public_url":"https:\/\/www.thingiverse.com\/davidnorman314","thumbnail":"https:\/\/www.thingiverse.com\/img\/default\/avatar\/avatar_default_thumb_medium.jpg"},{"id":102369,"name":"Backfreundin","first_name":"","last_name":"","url":"https:\/\/api.thingiverse.com\/users\/Backfreundin","public_url":"https:\/\/www.thingiverse.com\/Backfreundin","thumbnail":"https:\/\/www.thingiverse.com\/img\/default\/avatar\/avatar_default_thumb_medium.jpg"},{"id":65029,"name":"IntelliTom","first_name":"","last_name":"","url":"https:\/\/api.thingiverse.com\/users\/IntelliTom","public_url":"https:\/\/www.thingiverse.com\/IntelliTom","thumbnail":"https:\/\/cdn.thingiverse.com\/renders\/7f\/cc\/a4\/9e\/a6\/IW-square-Logo-750_thumb_medium.jpg"},{"id":93589,"name":"patriciagnat","first_name":"","last_name":"","url":"https:\/\/api.thingiverse.com\/users\/patriciagnat","public_url":"https:\/\/www.thingiverse.com\/patriciagnat","thumbnail":"https:\/\/www.thingiverse.com\/img\/default\/avatar\/avatar_default_thumb_medium.jpg"},{"id":96135,"name":"f4grx","first_name":"Sebastien","last_name":"F4GRX","url":"https:\/\/api.thingiverse.com\/users\/f4grx","public_url":"https:\/\/www.thingiverse.com\/f4grx","thumbnail":"https:\/\/www.thingiverse.com\/img\/default\/avatar\/avatar_default_thumb_medium.jpg"},{"id":16416,"name":"ChristianSi","first_name":"Christian","last_name":"Siefkes","url":"https:\/\/api.thingiverse.com\/users\/ChristianSi","public_url":"https:\/\/www.thingiverse.com\/ChristianSi","thumbnail":"https:\/\/cdn.thingiverse.com\/renders\/7e\/70\/91\/f2\/93\/kiel-beach-2_thumb_medium.jpg"},{"id":18655,"name":"creuzerm","first_name":"Mike","last_name":"Creuzer","url":"https:\/\/api.thingiverse.com\/users\/creuzerm","public_url":"https:\/\/www.thingiverse.com\/creuzerm","thumbnail":"https:\/\/cdn.thingiverse.com\/renders\/5e\/42\/76\/b9\/ce\/IMG_20111220_201238_display_large_thumb_medium.jpg"},{"id":18720,"name":"fukanchik","first_name":"Sergey","last_name":"","url":"https:\/\/api.thingiverse.com\/users\/fukanchik","public_url":"https:\/\/www.thingiverse.com\/fukanchik","thumbnail":"https:\/\/cdn.thingiverse.com\/renders\/c7\/c0\/2f\/40\/91\/falcon_display_large_thumb_medium.jpg"},{"id":26046,"name":"sergiolbpaludo","first_name":"sergio","last_name":"","url":"https:\/\/api.thingiverse.com\/users\/sergiolbpaludo","public_url":"https:\/\/www.thingiverse.com\/sergiolbpaludo","thumbnail":"https:\/\/cdn.thingiverse.com\/renders\/23\/41\/bf\/e5\/86\/IMG_20130312_191142_658_thumb_medium.jpg"},{"id":19645,"name":"llluis","first_name":"Luis","last_name":"Andrade","url":"https:\/\/api.thingiverse.com\/users\/llluis","public_url":"https:\/\/www.thingiverse.com\/llluis","thumbnail":"https:\/\/cdn.thingiverse.com\/renders\/24\/2c\/3d\/d3\/fb\/prusa_display_large_thumb_medium.jpg"},{"id":37949,"name":"rmoro","first_name":"Robert","last_name":"Moro","url":"https:\/\/api.thingiverse.com\/users\/rmoro","public_url":"https:\/\/www.thingiverse.com\/rmoro","thumbnail":"https:\/\/cdn.thingiverse.com\/renders\/8d\/f8\/5d\/7a\/e1\/robert_200_1024x768_thumb_medium.jpg"},{"id":51496,"name":"Ntropy","first_name":"","last_name":"","url":"https:\/\/api.thingiverse.com\/users\/Ntropy","public_url":"https:\/\/www.thingiverse.com\/Ntropy","thumbnail":"https:\/\/www.thingiverse.com\/img\/default\/avatar\/avatar_default_thumb_medium.jpg"},{"id":53173,"name":"kancelas","first_name":"","last_name":"","url":"https:\/\/api.thingiverse.com\/users\/kancelas","public_url":"https:\/\/www.thingiverse.com\/kancelas","thumbnail":"https:\/\/www.thingiverse.com\/img\/default\/avatar\/avatar_maker_thumb_medium.jpg"},{"id":32221,"name":"-SF-","first_name":"-SF-","last_name":"","url":"https:\/\/api.thingiverse.com\/users\/-SF-","public_url":"https:\/\/www.thingiverse.com\/-SF-","thumbnail":"https:\/\/www.thingiverse.com\/img\/default\/avatar\/avatar_default_thumb_medium.jpg"},{"id":42627,"name":"sporekat","first_name":"Kate","last_name":"P","url":"https:\/\/api.thingiverse.com\/users\/sporekat","public_url":"https:\/\/www.thingiverse.com\/sporekat","thumbnail":"https:\/\/www.thingiverse.com\/img\/default\/avatar\/avatar_default_thumb_medium.jpg"},{"id":50973,"name":"intropedro","first_name":"intropedro","last_name":"","url":"https:\/\/api.thingiverse.com\/users\/intropedro","public_url":"https:\/\/www.thingiverse.com\/intropedro","thumbnail":"https:\/\/cdn.thingiverse.com\/renders\/ed\/42\/83\/b6\/66\/atila_the_chaser_is_watching_thumb_medium.jpg"},{"id":20184,"name":"elelectronlibre","first_name":"","last_name":"","url":"https:\/\/api.thingiverse.com\/users\/elelectronlibre","public_url":"https:\/\/www.thingiverse.com\/elelectronlibre","thumbnail":"https:\/\/www.thingiverse.com\/img\/default\/avatar\/avatar_default_thumb_medium.jpg"},{"id":40689,"name":"jonasbits","first_name":"Jonas","last_name":"Anton ","url":"https:\/\/api.thingiverse.com\/users\/jonasbits","public_url":"https:\/\/www.thingiverse.com\/jonasbits","thumbnail":"https:\/\/cdn.thingiverse.com\/renders\/58\/48\/4c\/89\/29\/4x13-cap-538_thumb_medium.jpg"},{"id":46202,"name":"hole19","first_name":"Lele","last_name":"","url":"https:\/\/api.thingiverse.com\/users\/hole19","public_url":"https:\/\/www.thingiverse.com\/hole19","thumbnail":"https:\/\/cdn.thingiverse.com\/renders\/06\/66\/7e\/19\/20\/bf7742c4f32ddb79eda308f41d25821b_thumb_medium.jpg"},{"id":9515,"name":"gomezlendinez","first_name":"Daniel","last_name":"Gomez","url":"https:\/\/api.thingiverse.com\/users\/gomezlendinez","public_url":"https:\/\/www.thingiverse.com\/gomezlendinez","thumbnail":"https:\/\/cdn.thingiverse.com\/renders\/90\/68\/99\/af\/8d\/P3240172_display_large_thumb_medium.jpg"},{"id":25033,"name":"jmonath","first_name":"Jon","last_name":"Monath","url":"https:\/\/api.thingiverse.com\/users\/jmonath","public_url":"https:\/\/www.thingiverse.com\/jmonath","thumbnail":"https:\/\/cdn.thingiverse.com\/renders\/4e\/d9\/e8\/ef\/47\/image001_thumb_medium.jpg"},{"id":19197,"name":"spencer","first_name":"Spencer","last_name":"","url":"https:\/\/api.thingiverse.com\/users\/spencer","public_url":"https:\/\/www.thingiverse.com\/spencer","thumbnail":"https:\/\/cdn.thingiverse.com\/renders\/81\/40\/e0\/16\/79\/hoop_fractal_thumb_medium.jpg"},{"id":14912,"name":"h0st1le","first_name":"Justin","last_name":"Penka","url":"https:\/\/api.thingiverse.com\/users\/h0st1le","public_url":"https:\/\/www.thingiverse.com\/h0st1le","thumbnail":"https:\/\/cdn.thingiverse.com\/renders\/a4\/a8\/d8\/94\/77\/avatar_6873a069ce3c_128_display_large_thumb_medium.jpg"},{"id":31633,"name":"skarab","first_name":"","last_name":"","url":"https:\/\/api.thingiverse.com\/users\/skarab","public_url":"https:\/\/www.thingiverse.com\/skarab","thumbnail":"https:\/\/cdn.thingiverse.com\/renders\/37\/b3\/35\/dc\/12\/mesdiscussions-7485_thumb_medium.jpg"},{"id":32549,"name":"ADALab","first_name":"ADALab","last_name":"","url":"https:\/\/api.thingiverse.com\/users\/ADALab","public_url":"https:\/\/www.thingiverse.com\/ADALab","thumbnail":"https:\/\/cdn.thingiverse.com\/renders\/87\/d1\/8c\/91\/ad\/3_thumb_medium.jpg"},{"id":7924,"name":"doktormtl","first_name":"Ed","last_name":"Garner","url":"https:\/\/api.thingiverse.com\/users\/doktormtl","public_url":"https:\/\/www.thingiverse.com\/doktormtl","thumbnail":"https:\/\/www.thingiverse.com\/img\/default\/avatar\/avatar_default_thumb_medium.jpg"},{"id":30433,"name":"kastner","first_name":"Erik","last_name":"Kastner","url":"https:\/\/api.thingiverse.com\/users\/kastner","public_url":"https:\/\/www.thingiverse.com\/kastner","thumbnail":"https:\/\/www.thingiverse.com\/img\/default\/avatar\/avatar_default_thumb_medium.jpg"},{"id":25212,"name":"fecalgames","first_name":"Fecal","last_name":"Games","url":"https:\/\/api.thingiverse.com\/users\/fecalgames","public_url":"https:\/\/www.thingiverse.com\/fecalgames","thumbnail":"https:\/\/cdn.thingiverse.com\/renders\/db\/68\/02\/6a\/18\/poomascot_display_large_thumb_medium.jpg"},{"id":25347,"name":"Camos","first_name":"Carlos","last_name":"Mostajo","url":"https:\/\/api.thingiverse.com\/users\/Camos","public_url":"https:\/\/www.thingiverse.com\/Camos","thumbnail":"https:\/\/cdn.thingiverse.com\/renders\/fd\/e7\/b9\/f0\/65\/pt_432ddd_thumb_medium.jpg"},{"id":28333,"name":"Rodrigopw","first_name":"Rodrigo","last_name":"Perez Weiss","url":"https:\/\/api.thingiverse.com\/users\/Rodrigopw","public_url":"https:\/\/www.thingiverse.com\/Rodrigopw","thumbnail":"https:\/\/cdn.thingiverse.com\/renders\/7f\/32\/bd\/ed\/9b\/lflrodri_thumb_medium.jpg"},{"id":24333,"name":"t00tie","first_name":"t00tie","last_name":"","url":"https:\/\/api.thingiverse.com\/users\/t00tie","public_url":"https:\/\/www.thingiverse.com\/t00tie","thumbnail":"https:\/\/cdn.thingiverse.com\/renders\/a6\/4b\/5f\/3b\/de\/cowtoon_310x233_thumb_medium.jpg"},{"id":25612,"name":"iPadNanito","first_name":"iPadNanito","last_name":"","url":"https:\/\/api.thingiverse.com\/users\/iPadNanito","public_url":"https:\/\/www.thingiverse.com\/iPadNanito","thumbnail":"https:\/\/cdn.thingiverse.com\/renders\/47\/8b\/5a\/04\/05\/Leo_0012_thumb_medium.jpg"},{"id":22765,"name":"Busybotz","first_name":"Mitch","last_name":"","url":"https:\/\/api.thingiverse.com\/users\/Busybotz","public_url":"https:\/\/www.thingiverse.com\/Busybotz","thumbnail":"https:\/\/www.thingiverse.com\/img\/default\/avatar\/avatar_default_thumb_medium.jpg"},{"id":17455,"name":"BESommer","first_name":"Bruce","last_name":"Sommer","url":"https:\/\/api.thingiverse.com\/users\/BESommer","public_url":"https:\/\/www.thingiverse.com\/BESommer","thumbnail":"https:\/\/cdn.thingiverse.com\/renders\/fc\/51\/ea\/a9\/26\/Bruce_Sommer_display_large_thumb_medium.jpg"},{"id":14156,"name":"iammagic","first_name":"Stephen","last_name":"Hawkins","url":"https:\/\/api.thingiverse.com\/users\/iammagic","public_url":"https:\/\/www.thingiverse.com\/iammagic","thumbnail":"https:\/\/cdn.thingiverse.com\/renders\/ff\/42\/c0\/c2\/3b\/Vale_MagicShow__20080620_110_display_large_thumb_medium.jpg"},{"id":18497,"name":"Gunsoft","first_name":"Gunsoft","last_name":"","url":"https:\/\/api.thingiverse.com\/users\/Gunsoft","public_url":"https:\/\/www.thingiverse.com\/Gunsoft","thumbnail":"https:\/\/cdn.thingiverse.com\/renders\/10\/f9\/1a\/8b\/77\/logo_ru_display_large_thumb_medium.jpg"},{"id":729,"name":"unrepentantgeek","first_name":"Matthew","last_name":"","url":"https:\/\/api.thingiverse.com\/users\/unrepentantgeek","public_url":"https:\/\/www.thingiverse.com\/unrepentantgeek","thumbnail":"https:\/\/cdn.thingiverse.com\/renders\/49\/97\/2b\/b4\/d6\/1494231_display_large_thumb_medium.jpg"},{"id":10213,"name":"MtDon","first_name":"Donald","last_name":"E. King","url":"https:\/\/api.thingiverse.com\/users\/MtDon","public_url":"https:\/\/www.thingiverse.com\/MtDon","thumbnail":"https:\/\/cdn.thingiverse.com\/renders\/49\/15\/d0\/72\/1c\/me_2012_01_thumb_medium.jpg"},{"id":15516,"name":"akimitsu","first_name":"The","last_name":"LED Artist","url":"https:\/\/api.thingiverse.com\/users\/akimitsu","public_url":"https:\/\/www.thingiverse.com\/akimitsu","thumbnail":"https:\/\/cdn.thingiverse.com\/renders\/a2\/eb\/0f\/82\/e2\/opening_display_large_thumb_medium.jpg"},{"id":1522,"name":"mifga","first_name":"Matt","last_name":"Griffin","url":"https:\/\/api.thingiverse.com\/users\/mifga","public_url":"https:\/\/www.thingiverse.com\/mifga","thumbnail":"https:\/\/cdn.thingiverse.com\/renders\/fb\/65\/92\/a3\/8e\/xxxHolic_Tampopo_display_large_thumb_medium.jpg"},{"id":3375,"name":"bigpaws","first_name":"William","last_name":"Griffith","url":"https:\/\/api.thingiverse.com\/users\/bigpaws","public_url":"https:\/\/www.thingiverse.com\/bigpaws","thumbnail":"https:\/\/cdn.thingiverse.com\/renders\/0c\/5a\/f0\/43\/e3\/me-web_display_large_thumb_medium.jpg"},{"id":14499,"name":"tlalexander","first_name":"Taylor","last_name":"Alexander","url":"https:\/\/api.thingiverse.com\/users\/tlalexander","public_url":"https:\/\/www.thingiverse.com\/tlalexander","thumbnail":"https:\/\/cdn.thingiverse.com\/renders\/53\/2f\/63\/62\/c9\/me_display_large_thumb_medium.jpg"},{"id":14607,"name":"CamDAX","first_name":"","last_name":"","url":"https:\/\/api.thingiverse.com\/users\/CamDAX","public_url":"https:\/\/www.thingiverse.com\/CamDAX","thumbnail":"https:\/\/cdn.thingiverse.com\/renders\/dc\/25\/51\/76\/e6\/Cam_001_thumb_medium.jpg"},{"id":12845,"name":"uveros","first_name":"Guy","last_name":"Dascalu","url":"https:\/\/api.thingiverse.com\/users\/uveros","public_url":"https:\/\/www.thingiverse.com\/uveros","thumbnail":"https:\/\/cdn.thingiverse.com\/renders\/f8\/ac\/63\/97\/d9\/IMG_0230%5B2_display_large_thumb_medium.jpg"},{"id":12452,"name":"TheMegaCorp","first_name":"Jay","last_name":"","url":"https:\/\/api.thingiverse.com\/users\/TheMegaCorp","public_url":"https:\/\/www.thingiverse.com\/TheMegaCorp","thumbnail":"https:\/\/cdn.thingiverse.com\/renders\/98\/f9\/96\/81\/a3\/Myself_27_display_large_thumb_medium.jpg"},{"id":10492,"name":"inventworld","first_name":"James","last_name":"Sesler","url":"https:\/\/api.thingiverse.com\/users\/inventworld","public_url":"https:\/\/www.thingiverse.com\/inventworld","thumbnail":"https:\/\/cdn.thingiverse.com\/renders\/cd\/f3\/f3\/1a\/5a\/boys_display_large_thumb_medium.jpg"},{"id":10783,"name":"shay1978","first_name":"Shay","last_name":"","url":"https:\/\/api.thingiverse.com\/users\/shay1978","public_url":"https:\/\/www.thingiverse.com\/shay1978","thumbnail":"https:\/\/cdn.thingiverse.com\/renders\/32\/72\/0e\/88\/bd\/22a0ef3e438ba3adc44c878ee92a2d50_thumb_medium.jpg"},{"id":9713,"name":"OZAR","first_name":"","last_name":"","url":"https:\/\/api.thingiverse.com\/users\/OZAR","public_url":"https:\/\/www.thingiverse.com\/OZAR","thumbnail":"https:\/\/cdn.thingiverse.com\/renders\/6e\/fd\/48\/fb\/94\/KeithOzar_display_medium_thumb_medium.jpg"},{"id":9621,"name":"WillGreene09","first_name":"","last_name":"","url":"https:\/\/api.thingiverse.com\/users\/WillGreene09","public_url":"https:\/\/www.thingiverse.com\/WillGreene09","thumbnail":"https:\/\/www.thingiverse.com\/img\/default\/avatar\/avatar_default_thumb_medium.jpg"},{"id":1113,"name":"schmarty","first_name":"Marty","last_name":"McGuire","url":"https:\/\/api.thingiverse.com\/users\/schmarty","public_url":"https:\/\/www.thingiverse.com\/schmarty","thumbnail":"https:\/\/cdn.thingiverse.com\/renders\/35\/b9\/62\/b8\/c5\/me_southside_display_large_thumb_medium.jpg"},{"id":10073,"name":"MiseryBot","first_name":"","last_name":"","url":"https:\/\/api.thingiverse.com\/users\/MiseryBot","public_url":"https:\/\/www.thingiverse.com\/MiseryBot","thumbnail":"https:\/\/cdn.thingiverse.com\/renders\/bc\/bc\/eb\/b8\/84\/MiseryPusher_OpenSCAD_ICON_display_large_thumb_medium.jpg"},{"id":10331,"name":"Lorvija","first_name":"","last_name":"","url":"https:\/\/api.thingiverse.com\/users\/Lorvija","public_url":"https:\/\/www.thingiverse.com\/Lorvija","thumbnail":"https:\/\/www.thingiverse.com\/img\/default\/avatar\/avatar_default_thumb_medium.jpg"},{"id":3173,"name":"tentakles","first_name":"","last_name":"","url":"https:\/\/api.thingiverse.com\/users\/tentakles","public_url":"https:\/\/www.thingiverse.com\/tentakles","thumbnail":"https:\/\/cdn.thingiverse.com\/renders\/6b\/72\/dd\/b0\/39\/Manuel_Antonio_Sloth_display_large_thumb_medium.jpg"},{"id":5788,"name":"jasay","first_name":"","last_name":"","url":"https:\/\/api.thingiverse.com\/users\/jasay","public_url":"https:\/\/www.thingiverse.com\/jasay","thumbnail":"https:\/\/www.thingiverse.com\/img\/default\/avatar\/avatar_engineer_thumb_medium.jpg"},{"id":5192,"name":"araspitfire","first_name":"","last_name":"","url":"https:\/\/api.thingiverse.com\/users\/araspitfire","public_url":"https:\/\/www.thingiverse.com\/araspitfire","thumbnail":"https:\/\/cdn.thingiverse.com\/renders\/8c\/2e\/6d\/18\/46\/937064269_DNHEC-O_display_large_thumb_medium.jpg"},{"id":2191,"name":"zgbot","first_name":"zgbot","last_name":"","url":"https:\/\/api.thingiverse.com\/users\/zgbot","public_url":"https:\/\/www.thingiverse.com\/zgbot","thumbnail":"https:\/\/cdn.thingiverse.com\/renders\/1b\/57\/ec\/b5\/28\/IMG_0151_thumb_medium.jpg"},{"id":9263,"name":"RobotHospital","first_name":"Robot","last_name":"Hospital!","url":"https:\/\/api.thingiverse.com\/users\/RobotHospital","public_url":"https:\/\/www.thingiverse.com\/RobotHospital","thumbnail":"https:\/\/cdn.thingiverse.com\/renders\/c9\/06\/81\/30\/9f\/RobotHospitalImage_display_large_thumb_medium.jpg"},{"id":9035,"name":"elspeth","first_name":"Lisa","last_name":"Smith","url":"https:\/\/api.thingiverse.com\/users\/elspeth","public_url":"https:\/\/www.thingiverse.com\/elspeth","thumbnail":"https:\/\/cdn.thingiverse.com\/renders\/4b\/70\/ae\/1c\/13\/me_in_white_display_large_thumb_medium.jpg"},{"id":9531,"name":"BenJackson","first_name":"Ben","last_name":"Jackson","url":"https:\/\/api.thingiverse.com\/users\/BenJackson","public_url":"https:\/\/www.thingiverse.com\/BenJackson","thumbnail":"https:\/\/cdn.thingiverse.com\/renders\/ae\/e3\/7d\/3d\/84\/gravatar_display_large_thumb_medium.jpg"},{"id":47,"name":"nycdesigner","first_name":"Jeff","last_name":"Rutzky","url":"https:\/\/api.thingiverse.com\/users\/nycdesigner","public_url":"https:\/\/www.thingiverse.com\/nycdesigner","thumbnail":"https:\/\/cdn.thingiverse.com\/renders\/40\/66\/a5\/48\/7e\/DES1GNER_thingy_display_large_thumb_medium.jpg"},{"id":847,"name":"theron","first_name":"Theron","last_name":"Trowbridge","url":"https:\/\/api.thingiverse.com\/users\/theron","public_url":"https:\/\/www.thingiverse.com\/theron","thumbnail":"https:\/\/cdn.thingiverse.com\/renders\/f6\/9f\/e5\/8b\/2e\/rushmore_avatar_2_display_large_thumb_medium.jpg"},{"id":308,"name":"obijuan","first_name":"Juan","last_name":"Gonzalez","url":"https:\/\/api.thingiverse.com\/users\/obijuan","public_url":"https:\/\/www.thingiverse.com\/obijuan","thumbnail":"https:\/\/cdn.thingiverse.com\/renders\/cc\/6f\/17\/32\/5f\/Obijuan_display_large_thumb_medium.jpg"},{"id":7901,"name":"BrianEnigma","first_name":"Brian","last_name":"Enigma","url":"https:\/\/api.thingiverse.com\/users\/BrianEnigma","public_url":"https:\/\/www.thingiverse.com\/BrianEnigma","thumbnail":"https:\/\/cdn.thingiverse.com\/renders\/98\/8a\/e0\/0a\/8a\/goggles-180_display_large_thumb_medium.jpg"},{"id":4951,"name":"DefiantZombie","first_name":"Adam","last_name":"Dobrinin","url":"https:\/\/api.thingiverse.com\/users\/DefiantZombie","public_url":"https:\/\/www.thingiverse.com\/DefiantZombie","thumbnail":"https:\/\/www.thingiverse.com\/img\/default\/avatar\/avatar_maker_thumb_medium.jpg"},{"id":4620,"name":"randyy","first_name":"Randy","last_name":"Young","url":"https:\/\/api.thingiverse.com\/users\/randyy","public_url":"https:\/\/www.thingiverse.com\/randyy","thumbnail":"https:\/\/cdn.thingiverse.com\/renders\/40\/61\/ed\/cd\/29\/DSC00302_display_large_thumb_medium.jpg"},{"id":5606,"name":"shortpier","first_name":"ShortPier","last_name":"Industries","url":"https:\/\/api.thingiverse.com\/users\/shortpier","public_url":"https:\/\/www.thingiverse.com\/shortpier","thumbnail":"https:\/\/cdn.thingiverse.com\/renders\/fb\/93\/dd\/b7\/30\/shortpier-thingiverse-icon_thumb_medium.jpg"},{"id":2713,"name":"bbriggstkd","first_name":"","last_name":"","url":"https:\/\/api.thingiverse.com\/users\/bbriggstkd","public_url":"https:\/\/www.thingiverse.com\/bbriggstkd","thumbnail":"https:\/\/cdn.thingiverse.com\/renders\/1f\/f4\/a0\/74\/84\/bbriggstkd_display_large_thumb_medium.jpg"},{"id":2960,"name":"Black_Angel","first_name":"William","last_name":"Petefish","url":"https:\/\/api.thingiverse.com\/users\/Black_Angel","public_url":"https:\/\/www.thingiverse.com\/Black_Angel","thumbnail":"https:\/\/cdn.thingiverse.com\/renders\/51\/88\/52\/81\/6b\/P4100086_display_large_thumb_medium.jpg"},{"id":2649,"name":"ljyang","first_name":"John","last_name":"Yang","url":"https:\/\/api.thingiverse.com\/users\/ljyang","public_url":"https:\/\/www.thingiverse.com\/ljyang","thumbnail":"https:\/\/cdn.thingiverse.com\/renders\/11\/09\/86\/be\/e9\/Cain_Boswell_Yang_97_display_large_thumb_medium.jpg"},{"id":7067,"name":"g00bd0g","first_name":"Gabriel","last_name":"DeVault","url":"https:\/\/api.thingiverse.com\/users\/g00bd0g","public_url":"https:\/\/www.thingiverse.com\/g00bd0g","thumbnail":"https:\/\/cdn.thingiverse.com\/renders\/00\/1d\/bc\/04\/4d\/Digitizing_display_large_thumb_medium.jpg"},{"id":7614,"name":"Jakezilla3","first_name":"Jacob","last_name":"","url":"https:\/\/api.thingiverse.com\/users\/Jakezilla3","public_url":"https:\/\/www.thingiverse.com\/Jakezilla3","thumbnail":"https:\/\/www.thingiverse.com\/img\/default\/avatar\/avatar_default_thumb_medium.jpg"},{"id":5100,"name":"stewartstarbuck","first_name":"Stewart","last_name":"Starbuck","url":"https:\/\/api.thingiverse.com\/users\/stewartstarbuck","public_url":"https:\/\/www.thingiverse.com\/stewartstarbuck","thumbnail":"https:\/\/cdn.thingiverse.com\/renders\/10\/a0\/f7\/3f\/35\/IMAG0195_display_large_thumb_medium.jpg"},{"id":6734,"name":"PieterBos","first_name":"Pieter","last_name":"Bos","url":"https:\/\/api.thingiverse.com\/users\/PieterBos","public_url":"https:\/\/www.thingiverse.com\/PieterBos","thumbnail":"https:\/\/cdn.thingiverse.com\/renders\/2f\/88\/09\/5c\/38\/me_display_large_thumb_medium.jpg"},{"id":7845,"name":"bryanandaimee","first_name":"Bryan","last_name":"","url":"https:\/\/api.thingiverse.com\/users\/bryanandaimee","public_url":"https:\/\/www.thingiverse.com\/bryanandaimee","thumbnail":"https:\/\/cdn.thingiverse.com\/renders\/ad\/a1\/a4\/07\/0e\/Myphotosmall_display_large_thumb_medium.jpg"},{"id":7556,"name":"scanlime","first_name":"Micah","last_name":"Scott","url":"https:\/\/api.thingiverse.com\/users\/scanlime","public_url":"https:\/\/www.thingiverse.com\/scanlime","thumbnail":"https:\/\/cdn.thingiverse.com\/renders\/91\/2b\/c3\/21\/de\/bw-mohawk-headshot_thumb_medium.jpeg"},{"id":5848,"name":"cnguyen_2011","first_name":"Chi","last_name":"","url":"https:\/\/api.thingiverse.com\/users\/cnguyen_2011","public_url":"https:\/\/www.thingiverse.com\/cnguyen_2011","thumbnail":"https:\/\/www.thingiverse.com\/img\/default\/avatar\/avatar_default_thumb_medium.jpg"},{"id":4332,"name":"Zh4x0r","first_name":"Zeno","last_name":"","url":"https:\/\/api.thingiverse.com\/users\/Zh4x0r","public_url":"https:\/\/www.thingiverse.com\/Zh4x0r","thumbnail":"https:\/\/cdn.thingiverse.com\/renders\/c9\/9e\/62\/7b\/2b\/Cyrus_display_large_thumb_medium.jpg"},{"id":2762,"name":"jjshortcut","first_name":"Jan-Jaap","last_name":"","url":"https:\/\/api.thingiverse.com\/users\/jjshortcut","public_url":"https:\/\/www.thingiverse.com\/jjshortcut","thumbnail":"https:\/\/cdn.thingiverse.com\/renders\/49\/5b\/c2\/5e\/49\/PC080001_%5B800x600_display_large_thumb_medium.jpg"},{"id":4138,"name":"JSR","first_name":"","last_name":"","url":"https:\/\/api.thingiverse.com\/users\/JSR","public_url":"https:\/\/www.thingiverse.com\/JSR","thumbnail":"https:\/\/cdn.thingiverse.com\/renders\/5e\/a4\/6a\/34\/20\/IMG_1311_display_large_thumb_medium.jpg"},{"id":2613,"name":"DLPlanes","first_name":"DLPlanes","last_name":"","url":"https:\/\/api.thingiverse.com\/users\/DLPlanes","public_url":"https:\/\/www.thingiverse.com\/DLPlanes","thumbnail":"https:\/\/cdn.thingiverse.com\/renders\/71\/02\/90\/33\/13\/Screen_Shot_2014-10-29_at_22.09.19_thumb_medium.jpg"},{"id":2307,"name":"nicholasclewis","first_name":"Nicholas","last_name":"C Lewis","url":"https:\/\/api.thingiverse.com\/users\/nicholasclewis","public_url":"https:\/\/www.thingiverse.com\/nicholasclewis","thumbnail":"https:\/\/cdn.thingiverse.com\/renders\/64\/7f\/2a\/74\/e9\/IMG_3191_display_large_thumb_medium.jpg"},{"id":3481,"name":"chrisdkk","first_name":"Chris","last_name":"Krueger","url":"https:\/\/api.thingiverse.com\/users\/chrisdkk","public_url":"https:\/\/www.thingiverse.com\/chrisdkk","thumbnail":"https:\/\/cdn.thingiverse.com\/renders\/70\/49\/1f\/1b\/a7\/30819_560530043107_196600382_32563464_5268879_n_display_large_thumb_medium.jpg"},{"id":3509,"name":"MakerGirl","first_name":"Laura","last_name":"","url":"https:\/\/api.thingiverse.com\/users\/MakerGirl","public_url":"https:\/\/www.thingiverse.com\/MakerGirl","thumbnail":"https:\/\/cdn.thingiverse.com\/renders\/17\/b5\/d6\/ee\/a6\/Laura_Hall_display_large_thumb_medium.jpg"},{"id":145,"name":"connors934","first_name":"Chris","last_name":"Connors","url":"https:\/\/api.thingiverse.com\/users\/connors934","public_url":"https:\/\/www.thingiverse.com\/connors934","thumbnail":"https:\/\/cdn.thingiverse.com\/renders\/25\/bb\/94\/ca\/af\/4604995781_b6af317fd9_b_preview_medium_display_large_thumb_medium.jpg"},{"id":3240,"name":"CraigRK","first_name":"Craig","last_name":"Kritzinger","url":"https:\/\/api.thingiverse.com\/users\/CraigRK","public_url":"https:\/\/www.thingiverse.com\/CraigRK","thumbnail":"https:\/\/cdn.thingiverse.com\/renders\/75\/76\/63\/ec\/6c\/Craig_display_large_thumb_medium.jpg"},{"id":1983,"name":"smwombat","first_name":"Sharon","last_name":"Morrison","url":"https:\/\/api.thingiverse.com\/users\/smwombat","public_url":"https:\/\/www.thingiverse.com\/smwombat","thumbnail":"https:\/\/cdn.thingiverse.com\/renders\/9a\/04\/f5\/f2\/1f\/icon_display_large_thumb_medium.jpg"},{"id":1539,"name":"drayde","first_name":"Andreas","last_name":"Kahler","url":"https:\/\/api.thingiverse.com\/users\/drayde","public_url":"https:\/\/www.thingiverse.com\/drayde","thumbnail":"https:\/\/cdn.thingiverse.com\/renders\/10\/fe\/ca\/c8\/27\/manga_me_200x200_display_large_thumb_medium.jpg"},{"id":2880,"name":"oremusi","first_name":"oremusi","last_name":"","url":"https:\/\/api.thingiverse.com\/users\/oremusi","public_url":"https:\/\/www.thingiverse.com\/oremusi","thumbnail":"https:\/\/cdn.thingiverse.com\/renders\/17\/66\/27\/8d\/55\/Perfil_display_large_thumb_medium.jpg"},{"id":2913,"name":"pmcall221","first_name":"Patrick","last_name":"Callahan","url":"https:\/\/api.thingiverse.com\/users\/pmcall221","public_url":"https:\/\/www.thingiverse.com\/pmcall221","thumbnail":"https:\/\/cdn.thingiverse.com\/renders\/fa\/83\/2c\/01\/9c\/me_display_large_thumb_medium.jpg"},{"id":2303,"name":"flatironjoe","first_name":"Joe","last_name":"","url":"https:\/\/api.thingiverse.com\/users\/flatironjoe","public_url":"https:\/\/www.thingiverse.com\/flatironjoe","thumbnail":"https:\/\/cdn.thingiverse.com\/renders\/05\/26\/71\/71\/51\/saddestsoldier800_display_large_thumb_medium.jpg"},{"id":2130,"name":"JadeKnight","first_name":"","last_name":"","url":"https:\/\/api.thingiverse.com\/users\/JadeKnight","public_url":"https:\/\/www.thingiverse.com\/JadeKnight","thumbnail":"https:\/\/cdn.thingiverse.com\/renders\/0d\/bc\/b3\/f0\/03\/Jade_Falcon2_display_large_thumb_medium.jpg"},{"id":1762,"name":"bjbsquared","first_name":"Brian","last_name":"Beebe","url":"https:\/\/api.thingiverse.com\/users\/bjbsquared","public_url":"https:\/\/www.thingiverse.com\/bjbsquared","thumbnail":"https:\/\/cdn.thingiverse.com\/renders\/27\/bd\/35\/2a\/bf\/MNTBKMe_display_large_thumb_medium.jpg"},{"id":1564,"name":"rhmorrison","first_name":"Robert","last_name":"H. Morrison","url":"https:\/\/api.thingiverse.com\/users\/rhmorrison","public_url":"https:\/\/www.thingiverse.com\/rhmorrison","thumbnail":"https:\/\/cdn.thingiverse.com\/renders\/06\/43\/14\/c1\/8f\/BOBM_display_large_thumb_medium.jpg"},{"id":1675,"name":"jstiltner","first_name":"Justin","last_name":"Stiltner","url":"https:\/\/api.thingiverse.com\/users\/jstiltner","public_url":"https:\/\/www.thingiverse.com\/jstiltner","thumbnail":"https:\/\/www.thingiverse.com\/img\/default\/avatar\/avatar_default_thumb_medium.jpg"},{"id":1517,"name":"Robotdad","first_name":"Marc","last_name":"Goodner","url":"https:\/\/api.thingiverse.com\/users\/Robotdad","public_url":"https:\/\/www.thingiverse.com\/Robotdad","thumbnail":"https:\/\/cdn.thingiverse.com\/renders\/2a\/7e\/3d\/7f\/93\/MarcGoodner_display_large_thumb_medium.jpg"},{"id":1507,"name":"BLNorris","first_name":"Brandon","last_name":"","url":"https:\/\/api.thingiverse.com\/users\/BLNorris","public_url":"https:\/\/www.thingiverse.com\/BLNorris","thumbnail":"https:\/\/cdn.thingiverse.com\/renders\/df\/1e\/6c\/c0\/70\/537671_1714300540217_1297093511_n_thumb_medium.jpg"},{"id":1234,"name":"bpijls","first_name":"Bas","last_name":"Pijls","url":"https:\/\/api.thingiverse.com\/users\/bpijls","public_url":"https:\/\/www.thingiverse.com\/bpijls","thumbnail":"https:\/\/cdn.thingiverse.com\/renders\/66\/5b\/77\/ac\/f7\/bassie_display_large_thumb_medium.jpg"},{"id":603,"name":"wulfdesign","first_name":"Larry","last_name":"James","url":"https:\/\/api.thingiverse.com\/users\/wulfdesign","public_url":"https:\/\/www.thingiverse.com\/wulfdesign","thumbnail":"https:\/\/cdn.thingiverse.com\/renders\/f8\/47\/8e\/f7\/47\/3524079864_e3db561082_o_display_large_thumb_medium.jpg"},{"id":1111,"name":"jrombousky","first_name":"","last_name":"","url":"https:\/\/api.thingiverse.com\/users\/jrombousky","public_url":"https:\/\/www.thingiverse.com\/jrombousky","thumbnail":"https:\/\/cdn.thingiverse.com\/renders\/3a\/2b\/a8\/0f\/b7\/2009-09-06160004_display_large_thumb_medium.jpg"},{"id":1390,"name":"laszlo","first_name":"arcol.hu","last_name":"","url":"https:\/\/api.thingiverse.com\/users\/laszlo","public_url":"https:\/\/www.thingiverse.com\/laszlo","thumbnail":"https:\/\/cdn.thingiverse.com\/renders\/c4\/ef\/2d\/89\/4e\/8090861787_2fb62c33cf_h_thumb_medium.jpg"},{"id":954,"name":"cathalgarvey","first_name":"Cathal","last_name":"","url":"https:\/\/api.thingiverse.com\/users\/cathalgarvey","public_url":"https:\/\/www.thingiverse.com\/cathalgarvey","thumbnail":"https:\/\/cdn.thingiverse.com\/renders\/b3\/14\/de\/6d\/e6\/ecebbecf28c2692aeb021597fbddb174_thumb_medium.jpg"},{"id":1215,"name":"jkeegan","first_name":"Jeff","last_name":"Keegan","url":"https:\/\/api.thingiverse.com\/users\/jkeegan","public_url":"https:\/\/www.thingiverse.com\/jkeegan","thumbnail":"https:\/\/cdn.thingiverse.com\/renders\/3b\/4f\/f3\/3b\/a4\/JeffMugg_display_large_thumb_medium.jpg"},{"id":1269,"name":"fbz","first_name":"","last_name":"","url":"https:\/\/api.thingiverse.com\/users\/fbz","public_url":"https:\/\/www.thingiverse.com\/fbz","thumbnail":"https:\/\/cdn.thingiverse.com\/renders\/d8\/63\/26\/c8\/11\/fbz_display_large_thumb_medium.jpg"},{"id":49,"name":"johl","first_name":"Jens","last_name":"Ohlig","url":"https:\/\/api.thingiverse.com\/users\/johl","public_url":"https:\/\/www.thingiverse.com\/johl","thumbnail":"https:\/\/cdn.thingiverse.com\/renders\/8c\/5c\/b2\/9f\/64\/2714385092_1643e62eca_o_display_large_thumb_medium.jpg"},{"id":940,"name":"Bophoto","first_name":"Bo","last_name":"Lorentzen","url":"https:\/\/api.thingiverse.com\/users\/Bophoto","public_url":"https:\/\/www.thingiverse.com\/Bophoto","thumbnail":"https:\/\/cdn.thingiverse.com\/renders\/9d\/8f\/c7\/93\/90\/Bo-square_display_large_thumb_medium.jpg"},{"id":159,"name":"DementedChihuahua","first_name":"Stanley","last_name":"Ames","url":"https:\/\/api.thingiverse.com\/users\/DementedChihuahua","public_url":"https:\/\/www.thingiverse.com\/DementedChihuahua","thumbnail":"https:\/\/cdn.thingiverse.com\/renders\/f6\/e3\/24\/28\/b1\/demchi_display_large_thumb_medium.jpg"},{"id":854,"name":"aylr","first_name":"","last_name":"","url":"https:\/\/api.thingiverse.com\/users\/aylr","public_url":"https:\/\/www.thingiverse.com\/aylr","thumbnail":"https:\/\/cdn.thingiverse.com\/renders\/42\/6a\/93\/73\/2d\/icon_display_large_thumb_medium.jpg"},{"id":793,"name":"builttospec","first_name":"Craig","last_name":"Berscheidt","url":"https:\/\/api.thingiverse.com\/users\/builttospec","public_url":"https:\/\/www.thingiverse.com\/builttospec","thumbnail":"https:\/\/cdn.thingiverse.com\/renders\/be\/9a\/6c\/91\/5c\/av-big_display_large_thumb_medium.jpg"},{"id":670,"name":"Exposure101","first_name":"Tyler","last_name":"","url":"https:\/\/api.thingiverse.com\/users\/Exposure101","public_url":"https:\/\/www.thingiverse.com\/Exposure101","thumbnail":"https:\/\/cdn.thingiverse.com\/renders\/76\/f5\/6a\/e2\/c9\/n68133540_33134106_8816_display_large_thumb_medium.jpg"},{"id":181,"name":"Erik","first_name":"Erik","last_name":"de Bruijn","url":"https:\/\/api.thingiverse.com\/users\/Erik","public_url":"https:\/\/www.thingiverse.com\/Erik","thumbnail":"https:\/\/cdn.thingiverse.com\/renders\/28\/47\/f6\/93\/14\/IMG_2808_display_large_thumb_medium.jpg"},{"id":5,"name":"jfunlap","first_name":"Jen","last_name":"Dunlap","url":"https:\/\/api.thingiverse.com\/users\/jfunlap","public_url":"https:\/\/www.thingiverse.com\/jfunlap","thumbnail":"https:\/\/cdn.thingiverse.com\/renders\/b4\/01\/50\/af\/60\/2178422004_5a309c8048_display_large_thumb_medium.jpg"},{"id":2,"name":"bre","first_name":"Bre","last_name":"","url":"https:\/\/api.thingiverse.com\/users\/bre","public_url":"https:\/\/www.thingiverse.com\/bre","thumbnail":"https:\/\/cdn.thingiverse.com\/renders\/15\/c7\/e0\/eb\/7f\/4433868118_9766775a86_o_display_large_thumb_medium.jpg"}]